<annotation>
	<folder>plates</folder>
	<filename>SZA679_6.jpg</filename>
	<path>D:\2_lehre\2_lab_object_detection\1_lpr_detection+ocr\plates\SZA679_6.jpg</path>
	<source>
		<database>Unknown</database>
	</source>
	<size>
		<width>90</width>
		<height>45</height>
		<depth>1</depth>
	</size>
	<segmented>0</segmented>
	<object>
		<name>S</name>
		<pose>Unspecified</pose>
		<truncated>0</truncated>
		<difficult>0</difficult>
		<bndbox>
			<xmin>6</xmin>
			<ymin>11</ymin>
			<xmax>17</xmax>
			<ymax>31</ymax>
		</bndbox>
	</object>
	<object>
		<name>Z</name>
		<pose>Unspecified</pose>
		<truncated>0</truncated>
		<difficult>0</difficult>
		<bndbox>
			<xmin>18</xmin>
			<ymin>10</ymin>
			<xmax>28</xmax>
			<ymax>32</ymax>
		</bndbox>
	</object>
	<object>
		<name>A</name>
		<pose>Unspecified</pose>
		<truncated>0</truncated>
		<difficult>0</difficult>
		<bndbox>
			<xmin>28</xmin>
			<ymin>11</ymin>
			<xmax>39</xmax>
			<ymax>31</ymax>
		</bndbox>
	</object>
	<object>
		<name>6</name>
		<pose>Unspecified</pose>
		<truncated>0</truncated>
		<difficult>0</difficult>
		<bndbox>
			<xmin>50</xmin>
			<ymin>11</ymin>
			<xmax>61</xmax>
			<ymax>32</ymax>
		</bndbox>
	</object>
	<object>
		<name>7</name>
		<pose>Unspecified</pose>
		<truncated>0</truncated>
		<difficult>0</difficult>
		<bndbox>
			<xmin>61</xmin>
			<ymin>10</ymin>
			<xmax>73</xmax>
			<ymax>32</ymax>
		</bndbox>
	</object>
	<object>
		<name>9</name>
		<pose>Unspecified</pose>
		<truncated>0</truncated>
		<difficult>0</difficult>
		<bndbox>
			<xmin>73</xmin>
			<ymin>11</ymin>
			<xmax>83</xmax>
			<ymax>32</ymax>
		</bndbox>
	</object>
	<object>
		<name>None</name>
		<pose>Unspecified</pose>
		<truncated>0</truncated>
		<difficult>0</difficult>
		<bndbox>
			<xmin>39</xmin>
			<ymin>11</ymin>
			<xmax>50</xmax>
			<ymax>32</ymax>
		</bndbox>
	</object>
	<object>
		<name>None</name>
		<pose>Unspecified</pose>
		<truncated>1</truncated>
		<difficult>0</difficult>
		<bndbox>
			<xmin>1</xmin>
			<ymin>11</ymin>
			<xmax>6</xmax>
			<ymax>31</ymax>
		</bndbox>
	</object>
	<object>
		<name>None</name>
		<pose>Unspecified</pose>
		<truncated>1</truncated>
		<difficult>0</difficult>
		<bndbox>
			<xmin>83</xmin>
			<ymin>11</ymin>
			<xmax>90</xmax>
			<ymax>32</ymax>
		</bndbox>
	</object>
</annotation>
