<annotation>
	<folder>plates</folder>
	<filename>TNP222_6.jpg</filename>
	<path>D:\2_lehre\2_lab_object_detection\1_lpr_detection+ocr\plates\TNP222_6.jpg</path>
	<source>
		<database>Unknown</database>
	</source>
	<size>
		<width>67</width>
		<height>33</height>
		<depth>1</depth>
	</size>
	<segmented>0</segmented>
	<object>
		<name>T</name>
		<pose>Unspecified</pose>
		<truncated>0</truncated>
		<difficult>0</difficult>
		<bndbox>
			<xmin>4</xmin>
			<ymin>11</ymin>
			<xmax>13</xmax>
			<ymax>28</ymax>
		</bndbox>
	</object>
	<object>
		<name>N</name>
		<pose>Unspecified</pose>
		<truncated>0</truncated>
		<difficult>0</difficult>
		<bndbox>
			<xmin>13</xmin>
			<ymin>11</ymin>
			<xmax>24</xmax>
			<ymax>27</ymax>
		</bndbox>
	</object>
	<object>
		<name>P</name>
		<pose>Unspecified</pose>
		<truncated>0</truncated>
		<difficult>0</difficult>
		<bndbox>
			<xmin>22</xmin>
			<ymin>9</ymin>
			<xmax>30</xmax>
			<ymax>26</ymax>
		</bndbox>
	</object>
	<object>
		<name>2</name>
		<pose>Unspecified</pose>
		<truncated>0</truncated>
		<difficult>0</difficult>
		<bndbox>
			<xmin>38</xmin>
			<ymin>8</ymin>
			<xmax>47</xmax>
			<ymax>24</ymax>
		</bndbox>
	</object>
	<object>
		<name>2</name>
		<pose>Unspecified</pose>
		<truncated>0</truncated>
		<difficult>0</difficult>
		<bndbox>
			<xmin>46</xmin>
			<ymin>6</ymin>
			<xmax>55</xmax>
			<ymax>23</ymax>
		</bndbox>
	</object>
	<object>
		<name>2</name>
		<pose>Unspecified</pose>
		<truncated>0</truncated>
		<difficult>0</difficult>
		<bndbox>
			<xmin>54</xmin>
			<ymin>5</ymin>
			<xmax>63</xmax>
			<ymax>22</ymax>
		</bndbox>
	</object>
	<object>
		<name>None</name>
		<pose>Unspecified</pose>
		<truncated>0</truncated>
		<difficult>0</difficult>
		<bndbox>
			<xmin>30</xmin>
			<ymin>7</ymin>
			<xmax>38</xmax>
			<ymax>25</ymax>
		</bndbox>
	</object>
	<object>
		<name>None</name>
		<pose>Unspecified</pose>
		<truncated>1</truncated>
		<difficult>0</difficult>
		<bndbox>
			<xmin>1</xmin>
			<ymin>11</ymin>
			<xmax>5</xmax>
			<ymax>28</ymax>
		</bndbox>
	</object>
</annotation>
